fast500triples/__init__.py
fast500triples/__main__.py
fast500triples/sum.so
fast500triples/triples.py
fast500triples-1.0.4.dist-info/METADATA
fast500triples-1.0.4.dist-info/WHEEL
fast500triples-1.0.4.dist-info/top_level.txt
fast500triples-1.0.4.dist-info/RECORD
