Metadata-Version: 2.1
Name: fast500triples
Version: 1.0.4
Summary: Generate first 500 Pythagorean triples in no time.
Home-page: https://github.com/ShahidYousuf
Author: Shahid Yousuf
Author-email: shahidyousuf77@gmail.com
License: MIT
Platform: UNKNOWN
Classifier: License :: OSI Approved :: MIT License
Classifier: Programming Language :: Python :: 3
Classifier: Programming Language :: Python :: 3.5
